<?xml version="1.0" encoding="iso-8859-1"?>
<page xmlns:nb="http://www.emoveo.de/netbiscuits" title="News"> 

   <styles>
		    <style name="link-color" value="#D90000"/>
   </styles>

   <container>
	     <column>
		       <IMAGEHEADER fillcolor="D90000" boxing="3">
            <styles>
				           <style name="bgcolor" value="#D90000"/>
			         </styles>
            <img src="./res/generic-header-image.jpg" href="home.xml" alt="home"/>
         </IMAGEHEADER>
		       <BUTTONMENU>
            <styles>
               <style name="bgcolor" value="#d90000"/>
               <style name="active-color" value="#cccccc"/>
               <style name="active-bgcolor" value="#d90000"/>
               <style name="inactive-color" value="#FFFFFF"/>
               <style name="inactive-bgcolor" value="#d90000"/>
   		       </styles>
            <items>
	  			         <item>
	  				           <link href="home.xml">home</link>
	  			         </item>
	  			         <item active="true">
	  				           <link href="news.xml">news</link>
	  			         </item>
	  			         <item>
	  				           <link href="products.xml">products</link>
	  			         </item>
	  			         <item>
	  				           <link href="services.xml">services</link>
	  			         </item>
			         </items>
         </BUTTONMENU>
		       <SEPARATOR>
            <hr/>
         </SEPARATOR>
	     </column>
   </container>

   <container>
	     <column>
		       <SEPARATOR/>
		       <TEASER>
            <styles>
			</styles>
            <richtext align="right">[b]Headline News 1[/b][br][br][url="newscontent.xml"]Teaser Text of your featured news here.[/url]
			</richtext>
            <img src="res/article.gif" alt="myImage"/>
         </TEASER>
		       <SEPARATOR/>
		       <SEPARATOR>
            <hr/>
         </SEPARATOR>
	     </column>
   </container>

   <container>
	     <column>
		       <LIST cols="1">
            <styles>
	  </styles>
            <items>
			            <item>
				              <img src="res/arrow-right.gif" alt="*"/> 
				              <text href="newscontent.xml">
					Headline News 2 
				</text>
			            </item>
			            <item>
				              <img src="res/arrow-right.gif" alt="*"/> 
				              <text href="newscontent.xml">
					Headline News 3 
				</text>
			            </item>
			            <item>
				              <img src="res/arrow-right.gif" alt="*"/> 
				              <text href="newscontent.xml">
					Headline News 4 
				</text>
			            </item>
			            <item>
				              <img src="res/arrow-right.gif" alt="*"/> 
				              <text href="newscontent.xml">
					Headline News 5 
				</text>
			            </item>
			            <item>
				              <img src="res/arrow-right.gif" alt="*"/> 
				              <text href="newscontent.xml">
					Headline News 6 
				</text>
			            </item>
		          </items>
         </LIST>
		       <SEPARATOR/>
		       <SEPARATOR>
            <hr/>
         </SEPARATOR>
	     </column>
   </container>

   <container>
	 	   <NAVIGATION separator=" ">
         <styles>
				        <style name="color" value="#D90000"/>
			      </styles>
         <prev href="home.xml">
				        <img src="res/arrow-left.gif"/>
				        <text>&gt;</text>
			      </prev>
         <text>page 1 of 3</text>
         <next href="newsmore.xml">
				        <img src="res/arrow-right.gif"/>
				        <text>&gt;</text>
			      </next>
      </NAVIGATION>
   </container>

   <container>
	     <column>
		       <PAGEFOOTER>
            <styles>
				           <style name="color" value="#FFFFFF"/>
				           <style name="link-color" value="#FFFFFF"/>
				           <style name="bgcolor" value="#db001b"/>
			         </styles>
            <item position="1">
			            <richtext>[b]home[/b]</richtext>
				           <link href="home.xml"/>
			         </item>
            <item position="2">
			            <richtext>     </richtext>
			         </item>
            <item position="3">
			            <richtext>[b]contact[/b]</richtext>
 				          <link href="contact.xml"/>
			         </item>
            <item position="4">
			            <text> |</text>
			         </item>
            <item position="5">
			            <richtext>[b]imprint[/b]</richtext>
 				          <link href="imprint.xml"/>
			         </item>
         </PAGEFOOTER>
	     </column>
   </container>

</page>